<SubmitCard name="unique name card" label="label card" description="" priority="">

    <Destination type="Queue* ou Worflow" name="name"/>

    <Devices>
        <Device name="nom du device" label="label du device"/>
        <Device name="nom du device" label="label du device"/>
    </Devices>

    <Parameters>
    
        <Parameter visibility="modifiable ou show* ou hidden" type="enum de type(text*, int, date, ..." name="name" 
        label="label" required="true* ou false" persist="true or false*">default Value</Parameter>
        
        <ParametersGroup label="label du groupe de paramètre">
            <Parameter></Parameter>
        </ParametersGroup>
                
                
        <ParametersGroup label="label du groupe de paramètre gffd">
            <Parameter>
            </Parameter>

            <Parameter>
            </Parameter>

            <Parameter>
            </Parameter>
        </ParametersGroup>

    </Parameters>

    <ExtraArgs>gfdg
    </ExtraArgs>
   
</SubmitCard>

